lsp/__init__.py
jedi_lsp_wrapper-0.0.1.dist-info/METADATA
jedi_lsp_wrapper-0.0.1.dist-info/WHEEL
jedi_lsp_wrapper-0.0.1.dist-info/licenses/LICENSE
jedi_lsp_wrapper-0.0.1.dist-info/RECORD
