Metadata-Version: 2.4
Name: jedi-lsp-wrapper
Version: 0.0.1
Summary: Python LSP service wrapper based on Jedi.
Project-URL: Homepage, https://github.com/algo-visualizer/pylsp
Project-URL: Repository, https://github.com/algo-visualizer/pylsp.git
Project-URL: Issues, https://github.com/algo-visualizer/pylsp/issues
Author-email: sweetbrulee <sparrowking002@gmail.com>
License: MIT License
License-File: LICENSE
Keywords: jedi,lsp
Requires-Python: ==3.13.*
Requires-Dist: docstring-to-markdown
Requires-Dist: jedi
